server.py
skypulse_mcp-0.1.0.dist-info/METADATA
skypulse_mcp-0.1.0.dist-info/WHEEL
skypulse_mcp-0.1.0.dist-info/top_level.txt
skypulse_mcp-0.1.0.dist-info/RECORD
