Metadata-Version: 2.4
Name: skypulse-mcp
Version: 0.1.0
Summary: Simple MCP server for weather
Requires-Python: >=3.11
Requires-Dist: httpx>=0.28.1
Requires-Dist: mcp[cli]>=1.10.1
